[
  {
    "id": "10",
    "createTime": "2024-3-19 09:41:41.301",
    "updateTime": "2024-3-19 09:41:41.301",
    "deleted_at": null,
    "parentId": "7",
    "name": "修改",
    "router": null,
    "perms": "base:sys:user:delete,base:sys:user:update",
    "type": 2,
    "icon": null,
    "orderNum": 0,
    "viewPath": null,
    "keepAlive": 1,
    "isShow": 1,
    "isInstall": 1,
    "menuType": "base"
  },
  {
    "id": "11",
    "createTime": "2024-3-19 09:41:41.301",
    "updateTime": "2024-3-19 09:41:41.301",
    "deleted_at": null,
    "parentId": "7",
    "name": "查询",
    "router": null,
    "perms": "base:sys:user:page,base:sys:user:list,base:sys:user:info",
    "type": 2,
    "icon": null,
    "orderNum": 0,
    "viewPath": null,
    "keepAlive": 1,
    "isShow": 1,
    "isInstall": 1,
    "menuType": "base"
  },
  {
    "id": "12",
    "createTime": "2024-3-19 09:41:41.301",
    "updateTime": "2024-3-19 09:41:41.301",
    "deleted_at": null,
    "parentId": "7",
    "name": "部门列表",
    "router": null,
    "perms": "base:sys:department:list",
    "type": 2,
    "icon": null,
    "orderNum": 0,
    "viewPath": null,
    "keepAlive": 1,
    "isShow": 1,
    "isInstall": 1,
    "menuType": "base"
  },
  {
    "id": "13",
    "createTime": "2024-3-19 09:41:41.301",
    "updateTime": "2024-3-19 09:41:41.301",
    "deleted_at": null,
    "parentId": "7",
    "name": "新增部门",
    "router": null,
    "perms": "base:sys:department:add",
    "type": 2,
    "icon": null,
    "orderNum": 0,
    "viewPath": null,
    "keepAlive": 1,
    "isShow": 1,
    "isInstall": 1,
    "menuType": "base"
  },
  {
    "id": "14",
    "createTime": "2024-3-19 09:41:41.301",
    "updateTime": "2024-3-19 09:41:41.301",
    "deleted_at": null,
    "parentId": "7",
    "name": "更新部门",
    "router": null,
    "perms": "base:sys:department:update",
    "type": 2,
    "icon": null,
    "orderNum": 0,
    "viewPath": null,
    "keepAlive": 1,
    "isShow": 1,
    "isInstall": 1,
    "menuType": "base"
  },
  {
    "id": "15",
    "createTime": "2024-3-19 09:41:41.301",
    "updateTime": "2024-3-19 09:41:41.301",
    "deleted_at": null,
    "parentId": "7",
    "name": "删除部门",
    "router": null,
    "perms": "base:sys:department:delete",
    "type": 2,
    "icon": null,
    "orderNum": 0,
    "viewPath": null,
    "keepAlive": 1,
    "isShow": 1,
    "isInstall": 1,
    "menuType": "base"
  },
  {
    "id": "16",
    "createTime": "2024-3-19 09:41:41.301",
    "updateTime": "2024-3-19 09:41:41.301",
    "deleted_at": null,
    "parentId": "7",
    "name": "部门排序",
    "router": null,
    "perms": "base:sys:department:order",
    "type": 2,
    "icon": null,
    "orderNum": 0,
    "viewPath": null,
    "keepAlive": 1,
    "isShow": 1,
    "isInstall": 1,
    "menuType": "base"
  },
  {
    "id": "17",
    "createTime": "2024-3-19 09:41:41.301",
    "updateTime": "2024-3-19 09:41:41.301",
    "deleted_at": null,
    "parentId": "7",
    "name": "用户转移",
    "router": null,
    "perms": "base:sys:user:move",
    "type": 2,
    "icon": null,
    "orderNum": 0,
    "viewPath": null,
    "keepAlive": 1,
    "isShow": 1,
    "isInstall": 1,
    "menuType": "base"
  },
  {
    "id": "18",
    "createTime": "2024-3-19 09:41:41.301",
    "updateTime": "2024-3-19 09:41:41.301",
    "deleted_at": null,
    "parentId": "6",
    "name": "角色列表",
    "router": "/sys/role",
    "perms": null,
    "type": 1,
    "icon": "icon-common",
    "orderNum": 3,
    "viewPath": "modules/base/views/role.vue",
    "keepAlive": 1,
    "isShow": 1,
    "isInstall": 1,
    "menuType": "base"
  },
  {
    "id": "19",
    "createTime": "2024-3-19 09:41:41.301",
    "updateTime": "2024-3-19 09:41:41.301",
    "deleted_at": null,
    "parentId": "18",
    "name": "新增",
    "router": null,
    "perms": "base:sys:role:add",
    "type": 2,
    "icon": null,
    "orderNum": 0,
    "viewPath": null,
    "keepAlive": 0,
    "isShow": 1,
    "isInstall": 1,
    "menuType": "base"
  },
  {
    "id": "2",
    "createTime": "2024-3-19 09:41:41.301",
    "updateTime": "2024-3-19 09:41:41.301",
    "deleted_at": null,
    "parentId": null,
    "name": "系统管理",
    "router": null,
    "perms": null,
    "type": 0,
    "icon": "icon-system",
    "orderNum": 99,
    "viewPath": null,
    "keepAlive": 1,
    "isShow": 1,
    "isInstall": 1,
    "menuType": "base"
  },
  {
    "id": "20",
    "createTime": "2024-3-19 09:41:41.301",
    "updateTime": "2024-3-19 09:41:41.301",
    "deleted_at": null,
    "parentId": "18",
    "name": "删除",
    "router": null,
    "perms": "base:sys:role:delete",
    "type": 2,
    "icon": null,
    "orderNum": 0,
    "viewPath": null,
    "keepAlive": 0,
    "isShow": 1,
    "isInstall": 1,
    "menuType": "base"
  },
  {
    "id": "21",
    "createTime": "2024-3-19 09:41:41.301",
    "updateTime": "2024-3-19 09:41:41.301",
    "deleted_at": null,
    "parentId": "18",
    "name": "修改",
    "router": null,
    "perms": "base:sys:role:update",
    "type": 2,
    "icon": null,
    "orderNum": 0,
    "viewPath": null,
    "keepAlive": 0,
    "isShow": 1,
    "isInstall": 1,
    "menuType": "base"
  },
  {
    "id": "22",
    "createTime": "2024-3-19 09:41:41.301",
    "updateTime": "2024-3-19 09:41:41.301",
    "deleted_at": null,
    "parentId": "18",
    "name": "查询",
    "router": null,
    "perms": "base:sys:role:page,base:sys:role:list,base:sys:role:info",
    "type": 2,
    "icon": null,
    "orderNum": 0,
    "viewPath": null,
    "keepAlive": 0,
    "isShow": 1,
    "isInstall": 1,
    "menuType": "base"
  },
  {
    "id": "23",
    "createTime": "2024-3-19 09:41:41.301",
    "updateTime": "2024-3-19 09:41:41.301",
    "deleted_at": null,
    "parentId": "6",
    "name": "菜单列表",
    "router": "/sys/menu",
    "perms": null,
    "type": 1,
    "icon": "icon-menu",
    "orderNum": 2,
    "viewPath": "modules/base/views/menu.vue",
    "keepAlive": 1,
    "isShow": 1,
    "isInstall": 1,
    "menuType": "base"
  },
  {
    "id": "24",
    "createTime": "2024-3-19 09:41:41.301",
    "updateTime": "2024-3-19 09:41:41.301",
    "deleted_at": null,
    "parentId": "23",
    "name": "新增",
    "router": null,
    "perms": "base:sys:menu:add",
    "type": 2,
    "icon": null,
    "orderNum": 0,
    "viewPath": null,
    "keepAlive": 0,
    "isShow": 1,
    "isInstall": 1,
    "menuType": "base"
  },
  {
    "id": "25",
    "createTime": "2024-3-19 09:41:41.301",
    "updateTime": "2024-3-19 09:41:41.301",
    "deleted_at": null,
    "parentId": "23",
    "name": "删除",
    "router": null,
    "perms": "base:sys:menu:delete",
    "type": 2,
    "icon": null,
    "orderNum": 0,
    "viewPath": null,
    "keepAlive": 0,
    "isShow": 1,
    "isInstall": 1,
    "menuType": "base"
  },
  {
    "id": "26",
    "createTime": "2024-3-19 09:41:41.301",
    "updateTime": "2024-3-19 09:41:41.301",
    "deleted_at": null,
    "parentId": "23",
    "name": "修改",
    "router": null,
    "perms": "base:sys:menu:update",
    "type": 2,
    "icon": null,
    "orderNum": 0,
    "viewPath": null,
    "keepAlive": 0,
    "isShow": 1,
    "isInstall": 1,
    "menuType": "base"
  },
  {
    "id": "27",
    "createTime": "2024-3-19 09:41:41.301",
    "updateTime": "2024-3-19 09:41:41.301",
    "deleted_at": null,
    "parentId": "23",
    "name": "查询",
    "router": null,
    "perms": "base:sys:menu:page,base:sys:menu:list,base:sys:menu:info",
    "type": 2,
    "icon": null,
    "orderNum": 0,
    "viewPath": null,
    "keepAlive": 0,
    "isShow": 1,
    "isInstall": 1,
    "menuType": "base"
  },
  {
    "id": "28",
    "createTime": "2024-3-19 09:41:41.301",
    "updateTime": "2024-3-19 09:41:41.301",
    "deleted_at": null,
    "parentId": "2",
    "name": "参数配置",
    "router": null,
    "perms": null,
    "type": 0,
    "icon": "icon-common",
    "orderNum": 0,
    "viewPath": null,
    "keepAlive": 1,
    "isShow": 1,
    "isInstall": 1,
    "menuType": "base"
  },
  {
    "id": "29",
    "createTime": "2024-3-19 09:41:41.301",
    "updateTime": "2024-3-19 09:41:41.301",
    "deleted_at": null,
    "parentId": "28",
    "name": "参数列表",
    "router": "/sys/param",
    "perms": null,
    "type": 1,
    "icon": "icon-menu",
    "orderNum": 0,
    "viewPath": "modules/base/views/param.vue",
    "keepAlive": 1,
    "isShow": 1,
    "isInstall": 1,
    "menuType": "base"
  },
  {
    "id": "3",
    "createTime": "2024-3-19 09:41:41.301",
    "updateTime": "2024-3-19 09:41:41.301",
    "deleted_at": null,
    "parentId": "2",
    "name": "监控管理",
    "router": null,
    "perms": null,
    "type": 0,
    "icon": "icon-rank",
    "orderNum": 1,
    "viewPath": null,
    "keepAlive": 1,
    "isShow": 1,
    "isInstall": 1,
    "menuType": "base"
  },
  {
    "id": "30",
    "createTime": "2024-3-19 09:41:41.301",
    "updateTime": "2024-3-19 09:41:41.301",
    "deleted_at": null,
    "parentId": "28",
    "name": "新增",
    "router": null,
    "perms": "base:sys:param:add",
    "type": 2,
    "icon": null,
    "orderNum": 0,
    "viewPath": null,
    "keepAlive": 1,
    "isShow": 1,
    "isInstall": 1,
    "menuType": "base"
  },
  {
    "id": "31",
    "createTime": "2024-3-19 09:41:41.301",
    "updateTime": "2024-3-19 09:41:41.301",
    "deleted_at": null,
    "parentId": "28",
    "name": "修改",
    "router": null,
    "perms": "base:sys:param:info,base:sys:param:update",
    "type": 2,
    "icon": null,
    "orderNum": 0,
    "viewPath": null,
    "keepAlive": 1,
    "isShow": 1,
    "isInstall": 1,
    "menuType": "base"
  },
  {
    "id": "32",
    "createTime": "2024-3-19 09:41:41.301",
    "updateTime": "2024-3-19 09:41:41.301",
    "deleted_at": null,
    "parentId": "28",
    "name": "删除",
    "router": null,
    "perms": "base:sys:param:delete",
    "type": 2,
    "icon": null,
    "orderNum": 0,
    "viewPath": null,
    "keepAlive": 1,
    "isShow": 1,
    "isInstall": 1,
    "menuType": "base"
  },
  {
    "id": "33",
    "createTime": "2024-3-19 09:41:41.301",
    "updateTime": "2024-3-19 09:41:41.301",
    "deleted_at": null,
    "parentId": "28",
    "name": "查询",
    "router": null,
    "perms": "base:sys:param:page,base:sys:param:list,base:sys:param:info",
    "type": 2,
    "icon": null,
    "orderNum": 0,
    "viewPath": null,
    "keepAlive": 1,
    "isShow": 1,
    "isInstall": 1,
    "menuType": "base"
  },
  {
    "id": "4",
    "createTime": "2024-3-19 09:41:41.301",
    "updateTime": "2024-3-19 09:41:41.301",
    "deleted_at": null,
    "parentId": "3",
    "name": "请求日志",
    "router": "/sys/log",
    "perms": null,
    "type": 1,
    "icon": "icon-log",
    "orderNum": 0,
    "viewPath": "modules/base/views/log.vue",
    "keepAlive": 1,
    "isShow": 1,
    "isInstall": 1,
    "menuType": "base"
  },
  {
    "id": "45",
    "createTime": "2024-3-19 09:41:41.301",
    "updateTime": "2024-3-19 09:41:41.301",
    "deleted_at": null,
    "parentId": null,
    "name": "通用",
    "router": null,
    "perms": null,
    "type": 0,
    "icon": "icon-radioboxfill",
    "orderNum": 99,
    "viewPath": null,
    "keepAlive": 1,
    "isShow": 0,
    "isInstall": 1,
    "menuType": "base"
  },
  {
    "id": "49",
    "createTime": "2024-3-19 09:41:41.301",
    "updateTime": "2024-3-19 09:41:41.301",
    "deleted_at": null,
    "parentId": null,
    "name": "设置管理",
    "router": null,
    "perms": null,
    "type": 0,
    "icon": "icon-tag",
    "orderNum": 0,
    "viewPath": null,
    "keepAlive": 1,
    "isShow": 1,
    "isInstall": 1,
    "menuType": "base"
  },
  {
    "id": "5",
    "createTime": "2024-3-19 09:41:41.301",
    "updateTime": "2024-3-19 09:41:41.301",
    "deleted_at": null,
    "parentId": "4",
    "name": "权限",
    "router": null,
    "perms": "base:sys:log:page,base:sys:log:clear,base:sys:log:getKeep,base:sys:log:setKeep",
    "type": 2,
    "icon": null,
    "orderNum": 0,
    "viewPath": null,
    "keepAlive": 0,
    "isShow": 1,
    "isInstall": 1,
    "menuType": "base"
  },
  {
    "id": "50",
    "createTime": "2024-3-19 09:41:41.301",
    "updateTime": "2024-3-19 09:41:41.301",
    "deleted_at": null,
    "parentId": "49",
    "name": "站点配置",
    "router": "/base/setting",
    "perms": null,
    "type": 1,
    "icon": "icon-workbench",
    "orderNum": 1,
    "viewPath": "modules/base/views/setting.vue",
    "keepAlive": 1,
    "isShow": 1,
    "isInstall": 1,
    "menuType": "base"
  },
  {
    "id": "51",
    "createTime": "2024-3-19 09:41:41.301",
    "updateTime": "2024-3-19 09:41:41.301",
    "deleted_at": null,
    "parentId": "50",
    "name": "新增",
    "router": null,
    "perms": "base:sys:setting:add",
    "type": 2,
    "icon": null,
    "orderNum": 0,
    "viewPath": null,
    "keepAlive": 1,
    "isShow": 1,
    "isInstall": 1,
    "menuType": "base"
  },
  {
    "id": "52",
    "createTime": "2024-3-19 09:41:41.301",
    "updateTime": "2024-3-19 09:41:41.301",
    "deleted_at": null,
    "parentId": "50",
    "name": "删除",
    "router": null,
    "perms": "base:sys:setting:delete",
    "type": 2,
    "icon": null,
    "orderNum": 0,
    "viewPath": null,
    "keepAlive": 1,
    "isShow": 1,
    "isInstall": 1,
    "menuType": "base"
  },
  {
    "id": "53",
    "createTime": "2024-3-19 09:41:41.301",
    "updateTime": "2024-3-19 09:41:41.301",
    "deleted_at": null,
    "parentId": "50",
    "name": "修改",
    "router": null,
    "perms": "base:sys:setting:update",
    "type": 2,
    "icon": null,
    "orderNum": 0,
    "viewPath": null,
    "keepAlive": 0,
    "isShow": 1,
    "isInstall": 1,
    "menuType": "base"
  },
  {
    "id": "54",
    "createTime": "2024-3-19 09:41:41.301",
    "updateTime": "2024-3-19 09:41:41.301",
    "deleted_at": null,
    "parentId": "50",
    "name": "查询",
    "router": null,
    "perms": "base:sys:setting:page,base:sys:setting:list,base:sys:setting:info",
    "type": 2,
    "icon": null,
    "orderNum": 0,
    "viewPath": null,
    "keepAlive": 1,
    "isShow": 1,
    "isInstall": 1,
    "menuType": "base"
  },
  {
    "id": "6",
    "createTime": "2024-3-19 09:41:41.301",
    "updateTime": "2024-3-19 09:41:41.301",
    "deleted_at": null,
    "parentId": "2",
    "name": "权限管理",
    "router": null,
    "perms": null,
    "type": 0,
    "icon": "icon-auth",
    "orderNum": 2,
    "viewPath": null,
    "keepAlive": 0,
    "isShow": 1,
    "isInstall": 1,
    "menuType": "base"
  },
  {
    "id": "7",
    "createTime": "2024-3-19 09:41:41.301",
    "updateTime": "2024-3-19 09:41:41.301",
    "deleted_at": null,
    "parentId": "6",
    "name": "用户列表",
    "router": "/sys/user",
    "perms": null,
    "type": 1,
    "icon": "icon-user",
    "orderNum": 1,
    "viewPath": "modules/base/views/user.vue",
    "keepAlive": 1,
    "isShow": 1,
    "isInstall": 1,
    "menuType": "base"
  },
  {
    "id": "8",
    "createTime": "2024-3-19 09:41:41.301",
    "updateTime": "2024-3-19 09:41:41.301",
    "deleted_at": null,
    "parentId": "7",
    "name": "新增",
    "router": null,
    "perms": "base:sys:user:add",
    "type": 2,
    "icon": null,
    "orderNum": 0,
    "viewPath": null,
    "keepAlive": 1,
    "isShow": 1,
    "isInstall": 1,
    "menuType": "base"
  },
  {
    "id": "9",
    "createTime": "2024-3-19 09:41:41.301",
    "updateTime": "2024-3-19 09:41:41.301",
    "deleted_at": null,
    "parentId": "7",
    "name": "删除",
    "router": null,
    "perms": "base:sys:user:delete",
    "type": 2,
    "icon": null,
    "orderNum": 0,
    "viewPath": null,
    "keepAlive": 1,
    "isShow": 1,
    "isInstall": 1,
    "menuType": "base"
  },
  {
    "id" : "1771571678539681792",
    "createTime" : "'2024-03-24 00:16:17'",
    "updateTime" : "'2024-03-24 00:40:30.792'",
    "deleted_at" : null,
    "parentId" : "1769978559889149952",
    "name" : "installUpdateStatus",
    "router" : null,
    "perms" : "base:sys:addons:installUpdateStatus",
    "type" : 2,
    "icon" : null,
    "orderNum" : 0,
    "viewPath" : null,
    "keepAlive" : 1,
    "isShow" : 1,
    "isInstall" : 1,
    "menuType" : "base"
  },
  {
    "id" : "1771571495609307136",
    "createTime" : "'2024-03-24 00:15:33'",
    "updateTime" : "'2024-03-24 00:40:13.600'",
    "deleted_at" : null,
    "parentId" : "1769978559889149952",
    "name" : "lineUpdateStatus",
    "router" : null,
    "perms" : "base:sys:addons:lineUpdateStatus",
    "type" : 2,
    "icon" : null,
    "orderNum" : 0,
    "viewPath" : null,
    "keepAlive" : 1,
    "isShow" : 1,
    "isInstall" : 1,
    "menuType" : "base"
  },
  {
    "id" : "1771568553409908736",
    "createTime" : "'2024-03-24 00:03:51.942'",
    "updateTime" : "'2024-03-24 00:03:51.942'",
    "deleted_at" : null,
    "parentId" : "1769978559889149952",
    "name" : "typeListAndPage",
    "router" : null,
    "perms" : "base:sys:addonsType:list,base:sys:addonsType:page",
    "type" : 2,
    "icon" : null,
    "orderNum" : 0,
    "viewPath" : null,
    "keepAlive" : 1,
    "isShow" : 1,
    "isInstall" : 1,
    "menuType" : "base"
  },
  {
    "id" : "1771568433062744064",
    "createTime" : "'2024-03-24 00:03:23.249'",
    "updateTime" : "'2024-03-24 00:03:23.249'",
    "deleted_at" : null,
    "parentId" : "1769978559889149952",
    "name" : "typeInfoAndUpdate",
    "router" : null,
    "perms" : "base:sys:addonsType:update,base:sys:addonsType:info",
    "type" : 2,
    "icon" : null,
    "orderNum" : 0,
    "viewPath" : null,
    "keepAlive" : 1,
    "isShow" : 1,
    "isInstall" : 1,
    "menuType" : "base"
  },
  {
    "id" : "1771568249238982656",
    "createTime" : "'2024-03-24 00:02:39.422'",
    "updateTime" : "'2024-03-24 00:02:39.422'",
    "deleted_at" : null,
    "parentId" : "1769978559889149952",
    "name" : "typeDelete",
    "router" : null,
    "perms" : "base:sys:addonsType:delete",
    "type" : 2,
    "icon" : null,
    "orderNum" : 0,
    "viewPath" : null,
    "keepAlive" : 1,
    "isShow" : 1,
    "isInstall" : 1,
    "menuType" : "base"
  },
  {
    "id" : "1771568127927128064",
    "createTime" : "'2024-03-24 00:02:10.500'",
    "updateTime" : "'2024-03-24 00:02:10.500'",
    "deleted_at" : null,
    "parentId" : "1769978559889149952",
    "name" : "typeAdd",
    "router" : null,
    "perms" : "base:sys:addonsType:add",
    "type" : 2,
    "icon" : null,
    "orderNum" : 0,
    "viewPath" : null,
    "keepAlive" : 1,
    "isShow" : 1,
    "isInstall" : 1,
    "menuType" : "base"
  },
  {
    "id" : "1770006376253231104",
    "createTime" : "'2024-03-19 16:36:19.885'",
    "updateTime" : "'2024-03-19 16:36:19.885'",
    "deleted_at" : null,
    "parentId" : "1769978559889149952",
    "name" : "update",
    "router" : null,
    "perms" : "base:sys:addons:update",
    "type" : 2,
    "icon" : null,
    "orderNum" : 0,
    "viewPath" : null,
    "keepAlive" : 1,
    "isShow" : 1,
    "isInstall" : 1,
    "menuType" : "base"
  },
  {
    "id" : "1769978559939481600",
    "createTime" : "'2024-03-19 14:45:47.959'",
    "updateTime" : "'2024-03-19 14:45:47.959'",
    "deleted_at" : null,
    "parentId" : "1769978559889149952",
    "name" : "add",
    "router" : null,
    "perms" : "base:sys:addons:add",
    "type" : 2,
    "icon" : null,
    "orderNum" : 0,
    "viewPath" : null,
    "keepAlive" : 1,
    "isShow" : 1,
    "isInstall" : 1,
    "menuType" : "base"
  },
  {
    "id" : "1769978559939481601",
    "createTime" : "'2024-03-19 14:45:47.959'",
    "updateTime" : "'2024-03-19 14:45:47.959'",
    "deleted_at" : null,
    "parentId" : "1769978559889149952",
    "name" : "delete",
    "router" : null,
    "perms" : "base:sys:addons:delete",
    "type" : 2,
    "icon" : null,
    "orderNum" : 0,
    "viewPath" : null,
    "keepAlive" : 1,
    "isShow" : 1,
    "isInstall" : 1,
    "menuType" : "base"
  },
  {
    "id" : "1769978559939481602",
    "createTime" : "'2024-03-19 14:45:47.959'",
    "updateTime" : "'2024-03-19 14:45:47.959'",
    "deleted_at" : null,
    "parentId" : "1769978559889149952",
    "name" : "info",
    "router" : null,
    "perms" : "base:sys:addons:info",
    "type" : 2,
    "icon" : null,
    "orderNum" : 0,
    "viewPath" : null,
    "keepAlive" : 1,
    "isShow" : 1,
    "isInstall" : 1,
    "menuType" : "base"
  },
  {
    "id" : "1769978559939481603",
    "createTime" : "'2024-03-19 14:45:47.959'",
    "updateTime" : "'2024-03-19 14:45:47.959'",
    "deleted_at" : null,
    "parentId" : "1769978559889149952",
    "name" : "list",
    "router" : null,
    "perms" : "base:sys:addons:list",
    "type" : 2,
    "icon" : null,
    "orderNum" : 0,
    "viewPath" : null,
    "keepAlive" : 1,
    "isShow" : 1,
    "isInstall" : 1,
    "menuType" : "base"
  },
  {
    "id" : "1769978559939481604",
    "createTime" : "'2024-03-19 14:45:47.959'",
    "updateTime" : "'2024-03-19 14:45:47.959'",
    "deleted_at" : null,
    "parentId" : "1769978559889149952",
    "name" : "page",
    "router" : null,
    "perms" : "base:sys:addons:page",
    "type" : 2,
    "icon" : null,
    "orderNum" : 0,
    "viewPath" : null,
    "keepAlive" : 1,
    "isShow" : 1,
    "isInstall" : 1,
    "menuType" : "base"
  },
  {
    "id" : "1769978559889149952",
    "createTime" : "'2024-03-19 14:45:47'",
    "updateTime" : "'2024-03-19 14:48:32.573'",
    "deleted_at" : null,
    "parentId" : "1769910370463387648",
    "name" : "插件列表",
    "router" : "/base/addons",
    "perms" : null,
    "type" : 1,
    "icon" : "icon-common",
    "orderNum" : 1,
    "viewPath" : "modules/base/views/addons.vue",
    "keepAlive" : 1,
    "isShow" : 1,
    "isInstall" : 1,
    "menuType" : "base"
  },
  {
    "id" : "1769910370463387648",
    "createTime" : "'2024-03-19 10:14:50.321'",
    "updateTime" : "'2024-03-19 10:14:50.321'",
    "deleted_at" : null,
    "parentId" : null,
    "name" : "插件市场",
    "router" : null,
    "perms" : null,
    "type" : 0,
    "icon" : "icon-count",
    "orderNum" : 99,
    "viewPath" : null,
    "keepAlive" : 1,
    "isShow" : 1,
    "isInstall" : 1,
    "menuType" : "base"
  }





]